LICENSE
luzmo/__init__.py
luzmo/luzmo.py
luzmo_sdk-1.0.0.dist-info/entry_points.txt
luzmo_sdk-1.0.0.dist-info/METADATA
luzmo_sdk-1.0.0.dist-info/LICENSE
luzmo_sdk-1.0.0.dist-info/WHEEL
luzmo_sdk-1.0.0.dist-info/RECORD
