Metadata-Version: 2.1
Name: luzmo-sdk
Version: 1.0.0
Summary: Luzmo Python SDK for the Core API
Home-page: https://github.com/luzmo-official/luzmo-sdk-python
Author: Luzmo team
Author-email: engineering@luzmo.com
Requires-Python: >=3.6,<4.0
Classifier: Programming Language :: Python :: 3
Classifier: Programming Language :: Python :: 3.6
Classifier: Programming Language :: Python :: 3.7
Classifier: Programming Language :: Python :: 3.8
Classifier: Programming Language :: Python :: 3.9
Classifier: Programming Language :: Python :: 3.10
Classifier: Programming Language :: Python :: 3.11
Classifier: Topic :: Software Development :: Libraries :: Python Modules
Requires-Dist: requests (>=2.25.1,<3.0.0)
Project-URL: Repository, https://github.com/luzmo-official/luzmo-sdk-python
